sparcl/Results.py
sparcl/__init__.py
sparcl/client.py
sparcl/conf.py
sparcl/exceptions.py
sparcl/fields.py
sparcl/gather_2d.py
sparcl/resample_spectra.py
sparcl/sparc.ini
sparcl/type_conversion.py
sparcl/unsupported.py
sparcl/utils.py
sparcl/benchmarks/Benchmark_SPARCL_example.ipynb
sparcl/benchmarks/__init__.py
sparcl/benchmarks/benchmarks.py
sparcl/benchmarks/sparcl_benchmarking.ipynb
sparcl/notebooks/sparcl-examples.ipynb
sparclclient-1.2.8.dist-info/LICENSE
sparclclient-1.2.8.dist-info/WHEEL
sparclclient-1.2.8.dist-info/METADATA
sparclclient-1.2.8.dist-info/RECORD
