Metadata-Version: 2.3
Name: sparclclient
Version: 1.2.8
Summary: A client for getting spectra and meta-data from NOIRLab.
Author-email: "S. Pothier" <datalab-spectro@noirlab.edu>
Classifier: License :: OSI Approved :: MIT License
Requires-Dist: requests==2.31.0
Requires-Dist: numpy>=1.26,<2.4.0
Requires-Dist: spectres
Requires-Dist: pyjwt
Project-URL: Bug Tracker, https://github.com/pypa/sparclclient/issues
Project-URL: Documentation, https://sparclclient.readthedocs.io/en/latest/
Project-URL: Homepage, https://github.com/pypa/sparclclient
